{
  "remove": [
    "minecraft:trident"
  ],
  "values": [
    {
      "id": "#c:tools/spear",
      "required": false
    },
    {
      "id": "#justhammers:hammer",
      "required": false
    },
    {
      "id": "#curios:ring",
      "required": false
    },
    {
      "id": "twilightforest:block_and_chain",
      "required": false
    },
    {
      "id": "twilightforest:knightmetal_shield",
      "required": false
    },
    {
      "id": "twilightforest:naga_leggings",
      "required": false
    },
    {
      "id": "twilightforest:phantom_helmet",
      "required": false
    },
    {
      "id": "artifacts:fire_gauntlet",
      "required": false
    },
    {
      "id": "artifacts:golden_hook",
      "required": false
    },
    {
      "id": "artifacts:pickaxe_heater",
      "required": false
    },
    {
      "id": "artifacts:power_glove",
      "required": false
    },
    {
      "id": "artifacts:universal_attractor",
      "required": false
    },
    {
      "id": "artifacts:warp_drive",
      "required": false
    },
    {
      "id": "relics:drowned_belt",
      "required": false
    },
    {
      "id": "relics:holy_locket",
      "required": false
    },
    {
      "id": "relics:ice_breaker",
      "required": false
    },
    {
      "id": "mekanismtools:bronze_axe",
      "required": false
    },
    {
      "id": "mekanismtools:bronze_hoe",
      "required": false
    },
    {
      "id": "mekanismtools:bronze_paxel",
      "required": false
    },
    {
      "id": "mekanismtools:bronze_pickaxe",
      "required": false
    },
    {
      "id": "mekanismtools:bronze_shield",
      "required": false
    },
    {
      "id": "mekanismtools:bronze_shovel",
      "required": false
    },
    {
      "id": "mekanismtools:bronze_sword",
      "required": false
    },
    {
      "id": "mekanismtools:bronze_helmet",
      "required": false
    },
    {
      "id": "mekanismtools:bronze_chestplate",
      "required": false
    },
    {
      "id": "mekanismtools:bronze_leggings",
      "required": false
    },
    {
      "id": "mekanismtools:bronze_boots",
      "required": false
    },
    {
      "id": "mekanismtools:lapis_lazuli_axe",
      "required": false
    },
    {
      "id": "mekanismtools:lapis_lazuli_hoe",
      "required": false
    },
    {
      "id": "mekanismtools:lapis_lazuli_paxel",
      "required": false
    },
    {
      "id": "mekanismtools:lapis_lazuli_pickaxe",
      "required": false
    },
    {
      "id": "mekanismtools:lapis_lazuli_shield",
      "required": false
    },
    {
      "id": "mekanismtools:lapis_lazuli_shovel",
      "required": false
    },
    {
      "id": "mekanismtools:lapis_lazuli_sword",
      "required": false
    },
    {
      "id": "mekanismtools:lapis_lazuli_helmet",
      "required": false
    },
    {
      "id": "mekanismtools:lapis_lazuli_chestplate",
      "required": false
    },
    {
      "id": "mekanismtools:lapis_lazuli_leggings",
      "required": false
    },
    {
      "id": "mekanismtools:lapis_lazuli_boots",
      "required": false
    },
    {
      "id": "mekanismtools:osmium_axe",
      "required": false
    },
    {
      "id": "mekanismtools:osmium_hoe",
      "required": false
    },
    {
      "id": "mekanismtools:osmium_paxel",
      "required": false
    },
    {
      "id": "mekanismtools:osmium_pickaxe",
      "required": false
    },
    {
      "id": "mekanismtools:osmium_shield",
      "required": false
    },
    {
      "id": "mekanismtools:osmium_shovel",
      "required": false
    },
    {
      "id": "mekanismtools:osmium_sword",
      "required": false
    },
    {
      "id": "mekanismtools:osmium_helmet",
      "required": false
    },
    {
      "id": "mekanismtools:osmium_chestplate",
      "required": false
    },
    {
      "id": "mekanismtools:osmium_leggings",
      "required": false
    },
    {
      "id": "mekanismtools:osmium_boots",
      "required": false
    },
    {
      "id": "mekanismtools:refined_glowstone_axe",
      "required": false
    },
    {
      "id": "mekanismtools:refined_glowstone_hoe",
      "required": false
    },
    {
      "id": "mekanismtools:refined_glowstone_paxel",
      "required": false
    },
    {
      "id": "mekanismtools:refined_glowstone_pickaxe",
      "required": false
    },
    {
      "id": "mekanismtools:refined_glowstone_shield",
      "required": false
    },
    {
      "id": "mekanismtools:refined_glowstone_shovel",
      "required": false
    },
    {
      "id": "mekanismtools:refined_glowstone_sword",
      "required": false
    },
    {
      "id": "mekanismtools:refined_glowstone_helmet",
      "required": false
    },
    {
      "id": "mekanismtools:refined_glowstone_chestplate",
      "required": false
    },
    {
      "id": "mekanismtools:refined_glowstone_leggings",
      "required": false
    },
    {
      "id": "mekanismtools:refined_glowstone_boots",
      "required": false
    },
    {
      "id": "mekanismtools:refined_obsidian_axe",
      "required": false
    },
    {
      "id": "mekanismtools:refined_obsidian_hoe",
      "required": false
    },
    {
      "id": "mekanismtools:refined_obsidian_paxel",
      "required": false
    },
    {
      "id": "mekanismtools:refined_obsidian_pickaxe",
      "required": false
    },
    {
      "id": "mekanismtools:refined_obsidian_shield",
      "required": false
    },
    {
      "id": "mekanismtools:refined_obsidian_shovel",
      "required": false
    },
    {
      "id": "mekanismtools:refined_obsidian_sword",
      "required": false
    },
    {
      "id": "mekanismtools:refined_obsidian_helmet",
      "required": false
    },
    {
      "id": "mekanismtools:refined_obsidian_chestplate",
      "required": false
    },
    {
      "id": "mekanismtools:refined_obsidian_leggings",
      "required": false
    },
    {
      "id": "mekanismtools:refined_obsidian_boots",
      "required": false
    },
    {
      "id": "mekanismtools:steel_axe",
      "required": false
    },
    {
      "id": "mekanismtools:steel_hoe",
      "required": false
    },
    {
      "id": "mekanismtools:steel_paxel",
      "required": false
    },
    {
      "id": "mekanismtools:steel_pickaxe",
      "required": false
    },
    {
      "id": "mekanismtools:steel_shield",
      "required": false
    },
    {
      "id": "mekanismtools:steel_shovel",
      "required": false
    },
    {
      "id": "mekanismtools:steel_sword",
      "required": false
    },
    {
      "id": "mekanismtools:steel_helmet",
      "required": false
    },
    {
      "id": "mekanismtools:steel_chestplate",
      "required": false
    },
    {
      "id": "mekanismtools:steel_leggings",
      "required": false
    },
    {
      "id": "mekanismtools:steel_boots",
      "required": false
    },
    {
      "id": "mekanismtools:diamond_paxel",
      "required": false
    },
    {
      "id": "mekanismtools:gold_paxel",
      "required": false
    },
    {
      "id": "mekanismtools:iron_paxel",
      "required": false
    },
    {
      "id": "mekanismtools:stone_paxel",
      "required": false
    },
    {
      "id": "mekanismtools:wood_paxel",
      "required": false
    },
    {
      "id": "deeperdarker:resonarium_axe",
      "required": false
    },
    {
      "id": "deeperdarker:resonarium_boots",
      "required": false
    },
    {
      "id": "deeperdarker:resonarium_chestplate",
      "required": false
    },
    {
      "id": "deeperdarker:resonarium_helmet",
      "required": false
    },
    {
      "id": "deeperdarker:resonarium_hoe",
      "required": false
    },
    {
      "id": "deeperdarker:resonarium_leggings",
      "required": false
    },
    {
      "id": "deeperdarker:resonarium_pickaxe",
      "required": false
    },
    {
      "id": "deeperdarker:resonarium_shovel",
      "required": false
    },
    {
      "id": "deeperdarker:resonarium_sword",
      "required": false
    },
    {
      "id": "industrialforegoing:infinity_backpack",
      "required": false
    },
    {
      "id": "industrialforegoing:infinity_drill",
      "required": false
    },
    {
      "id": "industrialforegoing:infinity_hammer",
      "required": false
    },
    {
      "id": "industrialforegoing:infinity_launcher",
      "required": false
    },
    {
      "id": "industrialforegoing:infinity_saw",
      "required": false
    },
    {
      "id": "ars_elemental:air_bangle",
      "required": false
    },
    {
      "id": "ars_elemental:anima_bangle",
      "required": false
    },
    {
      "id": "ars_elemental:base_bangle",
      "required": false
    },
    {
      "id": "ars_elemental:earth_bangle",
      "required": false
    },
    {
      "id": "ars_elemental:fire_bangle",
      "required": false
    },
    {
      "id": "ars_elemental:summon_bangle",
      "required": false
    },
    {
      "id": "ars_elemental:water_bangle",
      "required": false
    },
    {
      "id": "twilightforest:fiery_boots",
      "required": false
    },
    {
      "id": "twilightforest:fiery_chestplate",
      "required": false
    },
    {
      "id": "twilightforest:fiery_helmet",
      "required": false
    },
    {
      "id": "twilightforest:fiery_leggings",
      "required": false
    },
    {
      "id": "twilightforest:fiery_sword",
      "required": false
    },
    {
      "id": "twilightforest:ironwood_boots",
      "required": false
    },
    {
      "id": "twilightforest:ironwood_chestplate",
      "required": false
    },
    {
      "id": "twilightforest:ironwood_helmet",
      "required": false
    },
    {
      "id": "twilightforest:ironwood_leggings",
      "required": false
    },
    {
      "id": "twilightforest:ironwood_sword",
      "required": false
    },
    {
      "id": "twilightforest:knightmetal_boots",
      "required": false
    },
    {
      "id": "twilightforest:knightmetal_chestplate",
      "required": false
    },
    {
      "id": "twilightforest:knightmetal_helmet",
      "required": false
    },
    {
      "id": "twilightforest:knightmetal_leggings",
      "required": false
    },
    {
      "id": "twilightforest:knightmetal_sword",
      "required": false
    },
    {
      "id": "twilightforest:steeleaf_boots",
      "required": false
    },
    {
      "id": "twilightforest:steeleaf_chestplate",
      "required": false
    },
    {
      "id": "twilightforest:steeleaf_helmet",
      "required": false
    },
    {
      "id": "twilightforest:steeleaf_leggings",
      "required": false
    },
    {
      "id": "twilightforest:steeleaf_sword",
      "required": false
    },
    {
      "id": "twilightforest:ironwood_hoe",
      "required": false
    },
    {
      "id": "twilightforest:ironwood_shovel",
      "required": false
    },
    {
      "id": "twilightforest:steeleaf_hoe",
      "required": false
    },
    {
      "id": "twilightforest:steeleaf_shovel",
      "required": false
    },
    {
      "id": "twilightforest:diamond_minotaur_axe",
      "required": false
    },
    {
      "id": "twilightforest:gold_minotaur_axe",
      "required": false
    },
    {
      "id": "twilightforest:ironwood_axe",
      "required": false
    },
    {
      "id": "twilightforest:knightmetal_axe",
      "required": false
    },
    {
      "id": "twilightforest:steeleaf_axe",
      "required": false
    },
    {
      "id": "twilightforest:fiery_pickaxe",
      "required": false
    },
    {
      "id": "twilightforest:ironwood_pickaxe",
      "required": false
    },
    {
      "id": "twilightforest:knightmetal_pickaxe",
      "required": false
    },
    {
      "id": "twilightforest:mazebreaker_pickaxe",
      "required": false
    },
    {
      "id": "twilightforest:steeleaf_pickaxe",
      "required": false
    },
    {
      "id": "twilightforest:naga_chestplate",
      "required": false
    },
    {
      "id": "twilightforest:phantom_chestplate",
      "required": false
    },
    {
      "id": "artifacts:flame_pendant",
      "required": false
    },
    {
      "id": "artifacts:shock_pendant",
      "required": false
    },
    {
      "id": "artifacts:thorn_pendant",
      "required": false
    },
    {
      "id": "artifacts:digging_claws",
      "required": false
    },
    {
      "id": "artifacts:feral_claws",
      "required": false
    },
    {
      "id": "artifacts:cross_necklace",
      "required": false
    },
    {
      "id": "artifacts:panic_necklace",
      "required": false
    },
    {
      "id": "artifacts:charm_of_shrinking",
      "required": false
    },
    {
      "id": "artifacts:charm_of_sinking",
      "required": false
    },
    {
      "id": "relics:ice_skates",
      "required": false
    },
    {
      "id": "relics:roller_skates",
      "required": false
    },
    {
      "id": "relics:jellyfish_necklace",
      "required": false
    },
    {
      "id": "relics:reflection_necklace",
      "required": false
    }
  ]
}